tabdpt/__init__.py
tabdpt/classifier.py
tabdpt/estimator.py
tabdpt/model.py
tabdpt/regressor.py
tabdpt/utils.py
tabdpt-1.1.11.dist-info/licenses/LICENSE
tabdpt-1.1.11.dist-info/METADATA
tabdpt-1.1.11.dist-info/WHEEL
tabdpt-1.1.11.dist-info/top_level.txt
tabdpt-1.1.11.dist-info/RECORD
