Metadata-Version: 2.4
Name: tabdpt
Version: 1.1.11
Summary: TabDPT: Scaling Tabular Foundation Models on Real Data
License-Expression: Apache-2.0
Project-URL: Repository, https://github.com/layer6ai-labs/TabDPT-inference
Project-URL: Paper, https://arxiv.org/abs/2410.18164
Project-URL: Model, https://huggingface.co/Layer6/TabDPT
Requires-Python: >=3.10
License-File: LICENSE
Requires-Dist: faiss-cpu<1.13.0,>=1.11.0
Requires-Dist: huggingface-hub<2.0,>=0.33.2
Requires-Dist: numpy<3.0,>=1.25.0
Requires-Dist: omegaconf<3.0,>=2.1.1
Requires-Dist: safetensors<1.0,>=0.5.3
Requires-Dist: scikit-learn<2.0,>=1.4.0
Requires-Dist: scipy<2.0,>=1.9.0
Requires-Dist: torch<3.0,>=2.6.0
Requires-Dist: tqdm<5.0,>=4.38.0
Provides-Extra: reproduce-results
Requires-Dist: faiss-cpu==1.11.0; extra == "reproduce-results"
Requires-Dist: numpy==2.3.0; python_version >= "3.11" and extra == "reproduce-results"
Requires-Dist: omegaconf==2.3.0; extra == "reproduce-results"
Requires-Dist: scikit-learn==1.7.0; extra == "reproduce-results"
Requires-Dist: scipy==1.15.3; extra == "reproduce-results"
Requires-Dist: torch==2.7.1; extra == "reproduce-results"
Requires-Dist: rliable==1.2.0; extra == "reproduce-results"
Requires-Dist: pandas==2.3.2; extra == "reproduce-results"
Requires-Dist: openml==0.15.1; extra == "reproduce-results"
Requires-Dist: jupyter==1.1.1; extra == "reproduce-results"
Requires-Dist: tenacity==9.1.2; extra == "reproduce-results"
Requires-Dist: gdown==5.2.0; extra == "reproduce-results"
Dynamic: license-file
